exobrain_entity_recognizer/__init__.py
exobrain_entity_recognizer/cli.py
exobrain_entity_recognizer/recognizer.py
exobrain_entity_recognizer-0.3.2.dist-info/METADATA
exobrain_entity_recognizer-0.3.2.dist-info/RECORD
exobrain_entity_recognizer-0.3.2.dist-info/WHEEL
exobrain_entity_recognizer-0.3.2.dist-info/entry_points.txt
exobrain_entity_recognizer-0.3.2.dist-info/top_level.txt
