Metadata-Version: 2.1
Name: exobrain-entity-recognizer
Version: 0.3.2
Summary: Entity recognizer for Exobrain project.
Home-page: https://github.com/kaist-irnlp/exobrain-entity-recognizer
Author: Kyoung-Rok Jang
Author-email: kyoungrok.jang@gmail.com
License: UNKNOWN
Keywords: exobrain_entity_recognizer
Platform: UNKNOWN
Classifier: Development Status :: 2 - Pre-Alpha
Classifier: Intended Audience :: Developers
Classifier: Natural Language :: English
Classifier: Programming Language :: Python :: 3.5
Classifier: Programming Language :: Python :: 3.6
Requires-Dist: Click (>=6.0)
Requires-Dist: spacy (<3.0,>=2.0)
Requires-Dist: ujson
Requires-Dist: textblob
